torch_geometric_edge/__init__.py
torch_geometric_edge/datasets/__init__.py
torch_geometric_edge/datasets/cora.py
torch_geometric_edge/datasets/cuneiform.py
torch_geometric_edge/datasets/dolphin.py
torch_geometric_edge/datasets/karateclub.py
torch_geometric_edge/datasets/pubmed.py
torch_geometric_edge/datasets/unsw.py
torch_geometric_edge/evaluation/__init__.py
torch_geometric_edge/evaluation/classification.py
torch_geometric_edge/models/__init__.py
torch_geometric_edge/models/attre2vec.py
torch_geometric_edge/models/ehgnn.py
torch_geometric_edge/models/line2vec.py
torch_geometric_edge/models/paire.py
torch_geometric_edge/nn/__init__.py
torch_geometric_edge/nn/node2edge.py
torch_geometric_edge/nn/node_pair_op.py
torch_geometric_edge/samplers/__init__.py
torch_geometric_edge/samplers/attre2vec.py
torch_geometric_edge/transforms/__init__.py
torch_geometric_edge/transforms/attre2vec.py
torch_geometric_edge/transforms/edge_label.py
torch_geometric_edge/transforms/line2vec.py
torch_geometric_edge-0.0.1.dist-info/LICENSE
torch_geometric_edge-0.0.1.dist-info/METADATA
torch_geometric_edge-0.0.1.dist-info/WHEEL
torch_geometric_edge-0.0.1.dist-info/top_level.txt
torch_geometric_edge-0.0.1.dist-info/RECORD
