Metadata-Version: 2.1
Name: torch-geometric-edge
Version: 0.0.1
Summary: Edge representation learning library
Home-page: 
Author: Piotr Bielak
Author-email: piotr.bielak@pwr.edu.pl
License: MIT
Requires-Python: >=3.8
License-File: LICENSE
Requires-Dist: gensim (>=4.2.0)
Requires-Dist: networkx (>=2.8.5)
Requires-Dist: pandas (>=1.4.3)
Requires-Dist: requests (>=2.28.1)
Requires-Dist: scikit-learn (>=1.1.1)
Requires-Dist: torch (>=1.10.0)
Requires-Dist: torch-geometric (==2.0.4)
Provides-Extra: test
Requires-Dist: flake8 ; extra == 'test'
Requires-Dist: isort ; extra == 'test'
Requires-Dist: pylint ; extra == 'test'
Requires-Dist: pytest ; extra == 'test'
